Metadata-Version: 2.1
Name: rtb-data
Version: 0.10.1
Summary: Data files for the Robotics Toolbox for Python.
Home-page: https://github.com/petercorke/roboticstoolbox-python
Author: Peter Corke
Author-email: rvc@petercorke.com
License: UNKNOWN
Project-URL: Source, https://github.com/petercorke/roboticstoolbox-python
Keywords: python robotics
Platform: UNKNOWN
Classifier: Development Status :: 5 - Production/Stable
Classifier: Intended Audience :: Developers
Classifier: License :: OSI Approved :: MIT License
Classifier: Programming Language :: Python :: 3 :: Only
